segmentation_skeleton_metrics/__init__.py
segmentation_skeleton_metrics/evaluate.py
segmentation_skeleton_metrics/skeleton_metrics.py
segmentation_skeleton_metrics/data_handling/graph_classes.py
segmentation_skeleton_metrics/data_handling/graph_loading.py
segmentation_skeleton_metrics/data_handling/swc_loading.py
segmentation_skeleton_metrics/utils/img_util.py
segmentation_skeleton_metrics/utils/util.py
segmentation_skeleton_metrics-5.6.14.dist-info/LICENSE
segmentation_skeleton_metrics-5.6.14.dist-info/METADATA
segmentation_skeleton_metrics-5.6.14.dist-info/WHEEL
segmentation_skeleton_metrics-5.6.14.dist-info/top_level.txt
segmentation_skeleton_metrics-5.6.14.dist-info/RECORD
