Metadata-Version: 2.1
Name: segmentation_skeleton_metrics
Version: 5.6.14
Summary: Python package for evaluating neuron segmentations in terms of the number of splits and merges
Author-email: Anna Grim <anna.grim@alleninstitute.org>
License: MIT
Classifier: Programming Language :: Python :: 3
Requires-Python: >=3.7
License-File: LICENSE
Requires-Dist: boto3
Requires-Dist: google-cloud-storage
Requires-Dist: networkx
Requires-Dist: numpy
Requires-Dist: pandas
Requires-Dist: s3fs
Requires-Dist: scikit-image
Requires-Dist: tensorstore
Requires-Dist: tifffile
Provides-Extra: dev
Requires-Dist: black ; extra == 'dev'
Requires-Dist: coverage ; extra == 'dev'
Requires-Dist: flake8 ; extra == 'dev'
Requires-Dist: interrogate ; extra == 'dev'
Requires-Dist: isort ; extra == 'dev'
Requires-Dist: Sphinx ; extra == 'dev'
Requires-Dist: pygit2 ; extra == 'dev'
Requires-Dist: furo ; extra == 'dev'
